rishabh12_1/__init__.py
rishabh12_1/sum.py
rishabh12_1-0.0.1.dist-info/METADATA
rishabh12_1-0.0.1.dist-info/WHEEL
rishabh12_1-0.0.1.dist-info/top_level.txt
rishabh12_1-0.0.1.dist-info/RECORD
