Metadata-Version: 2.1
Name: rishabh12-1
Version: 0.0.1
Summary: UNKNOWN
Home-page: UNKNOWN
Author: TCG (Rishabh)
Author-email: <rihabhk1@dewsolutions.in>
License: UNKNOWN
Keywords: python,aithrmatics
Platform: UNKNOWN
Classifier: Development Status :: 1 - Planning
Classifier: Intended Audience :: Developers
Classifier: Programming Language :: Python :: 3
Classifier: Operating System :: Unix
Classifier: Operating System :: MacOS :: MacOS X
Classifier: Operating System :: Microsoft :: Windows
Requires-Dist: pandas
